[
  {
    "inputs": [],
    "stateMutability": "nonpayable",
    "type": "constructor"
  },
  {
    "inputs": [],
    "name": "InsufficientDeploymentFee",
    "type": "error"
  },
  {
    "inputs": [],
    "name": "InvalidDeploymentFee",
    "type": "error"
  },
  {
    "inputs": [],
    "name": "InvalidInput",
    "type": "error"
  },
  {
    "anonymous": false,
    "inputs": [
      {
        "indexed": false,
        "internalType": "uint256",
        "name": "oldFee",
        "type": "uint256"
      },
      {
        "indexed": false,
        "internalType": "uint256",
        "name": "newFee",
        "type": "uint256"
      }
    ],
    "name": "DeploymentFeeUpdated",
    "type": "event"
  },
  {
    "anonymous": false,
    "inputs": [
      {
        "indexed": true,
        "internalType": "address",
        "name": "deployer",
        "type": "address"
      },
      {
        "indexed": true,
        "internalType": "address",
        "name": "token",
        "type": "address"
      },
      {
        "indexed": false,
        "internalType": "address",
        "name": "router",
        "type": "address"
      },
      {
        "indexed": false,
        "internalType": "address",
        "name": "strategy",
        "type": "address"
      },
      {
        "indexed": false,
        "internalType": "string",
        "name": "name",
        "type": "string"
      },
      {
        "indexed": false,
        "internalType": "string",
        "name": "symbol",
        "type": "string"
      },
      {
        "indexed": false,
        "internalType": "uint256",
        "name": "deploymentFee",
        "type": "uint256"
      }
    ],
    "name": "TokenDeployed",
    "type": "event"
  },
  {
    "inputs": [
      {
        "internalType": "string",
        "name": "_name",
        "type": "string"
      },
      {
        "internalType": "string",
        "name": "_symbol",
        "type": "string"
      },
      {
        "internalType": "address",
        "name": "_nftCollection",
        "type": "address"
      },
      {
        "internalType": "address",
        "name": "_collectionOwnerAddress",
        "type": "address"
      },
      {
        "internalType": "uint256",
        "name": "_royaltyBps",
        "type": "uint256"
      }
    ],
    "name": "deployStrategyToken",
    "outputs": [
      {
        "internalType": "address",
        "name": "token",
        "type": "address"
      },
      {
        "internalType": "address",
        "name": "router",
        "type": "address"
      },
      {
        "internalType": "address",
        "name": "strategy",
        "type": "address"
      }
    ],
    "stateMutability": "payable",
    "type": "function"
  },
  {
    "inputs": [],
    "name": "getDeploymentFee",
    "outputs": [
      {
        "internalType": "uint256",
        "name": "",
        "type": "uint256"
      }
    ],
    "stateMutability": "view",
    "type": "function"
  },
  {
    "inputs": [
      {
        "internalType": "address",
        "name": "token",
        "type": "address"
      }
    ],
    "name": "getTokenStrategy",
    "outputs": [
      {
        "internalType": "address",
        "name": "",
        "type": "address"
      }
    ],
    "stateMutability": "view",
    "type": "function"
  },
  {
    "inputs": [
      {
        "internalType": "address",
        "name": "user",
        "type": "address"
      }
    ],
    "name": "getUserTokens",
    "outputs": [
      {
        "internalType": "address[]",
        "name": "",
        "type": "address[]"
      }
    ],
    "stateMutability": "view",
    "type": "function"
  },
  {
    "inputs": [
      {
        "internalType": "address",
        "name": "token",
        "type": "address"
      }
    ],
    "name": "isDeployedToken",
    "outputs": [
      {
        "internalType": "bool",
        "name": "",
        "type": "bool"
      }
    ],
    "stateMutability": "view",
    "type": "function"
  },
  {
    "inputs": [],
    "name": "owner",
    "outputs": [
      {
        "internalType": "address",
        "name": "",
        "type": "address"
      }
    ],
    "stateMutability": "view",
    "type": "function"
  },
  {
    "inputs": [
      {
        "internalType": "uint256",
        "name": "newFee",
        "type": "uint256"
      }
    ],
    "name": "setDeploymentFee",
    "outputs": [],
    "stateMutability": "nonpayable",
    "type": "function"
  }
]

